dbt_cloud/__init__.py
dbt_cloud/cli.py
dbt_cloud/exc.py
dbt_cloud/field.py
dbt_cloud/serde.py
dbt_cloud/command/__init__.py
dbt_cloud/command/command.py
dbt_cloud/command/account/__init__.py
dbt_cloud/command/account/get.py
dbt_cloud/command/account/list.py
dbt_cloud/command/audit_log/__init__.py
dbt_cloud/command/audit_log/get.py
dbt_cloud/command/connection/__init__.py
dbt_cloud/command/connection/create.py
dbt_cloud/command/connection/delete.py
dbt_cloud/command/connection/get.py
dbt_cloud/command/connection/list.py
dbt_cloud/command/environment/__init__.py
dbt_cloud/command/environment/create.py
dbt_cloud/command/environment/delete.py
dbt_cloud/command/environment/get.py
dbt_cloud/command/environment/list.py
dbt_cloud/command/job/__init__.py
dbt_cloud/command/job/create.py
dbt_cloud/command/job/delete.py
dbt_cloud/command/job/get.py
dbt_cloud/command/job/list.py
dbt_cloud/command/job/run.py
dbt_cloud/command/metadata/__init__.py
dbt_cloud/command/metadata/query.py
dbt_cloud/command/project/__init__.py
dbt_cloud/command/project/create.py
dbt_cloud/command/project/delete.py
dbt_cloud/command/project/get.py
dbt_cloud/command/project/list.py
dbt_cloud/command/project/update.py
dbt_cloud/command/run/__init__.py
dbt_cloud/command/run/cancel.py
dbt_cloud/command/run/get.py
dbt_cloud/command/run/get_artifact.py
dbt_cloud/command/run/list.py
dbt_cloud/command/run/list_artifacts.py
dbt_cloud/demo/__init__.py
dbt_cloud/demo/catalog.py
dbt_cloud_cli-0.8.2.dist-info/LICENSE
dbt_cloud_cli-0.8.2.dist-info/METADATA
dbt_cloud_cli-0.8.2.dist-info/WHEEL
dbt_cloud_cli-0.8.2.dist-info/entry_points.txt
dbt_cloud_cli-0.8.2.dist-info/top_level.txt
dbt_cloud_cli-0.8.2.dist-info/RECORD
