Metadata-Version: 2.1
Name: dbt-cloud-cli
Version: 0.8.2
Summary: dbt Cloud command line interface (CLI)
Home-page: https://github.com/data-mie/dbt-cloud-cli
Author: Simo Tumelius
Author-email: simo@datamie.fi
License: Apache Software License
Platform: UNKNOWN
Classifier: License :: OSI Approved :: MIT License
Classifier: Programming Language :: Python :: 3
Classifier: Programming Language :: Python :: 3.6
Requires-Python: >=3.6
License-File: LICENSE
Requires-Dist: requests
Requires-Dist: click
Requires-Dist: pydantic (==1.10.10)
Requires-Dist: mergedeep
Provides-Extra: demo
Requires-Dist: inquirer ; extra == 'demo'
Requires-Dist: art ; extra == 'demo'
Provides-Extra: lint
Requires-Dist: black ; extra == 'lint'
Provides-Extra: test
Requires-Dist: pytest ; extra == 'test'
Requires-Dist: pytest-cov ; extra == 'test'
Requires-Dist: pytest-datadir ; extra == 'test'
Requires-Dist: requests-mock ; extra == 'test'
